cryptoserpent/SymmetricRSA.py
cryptoserpent/__init__.py
cryptoserpent-0.0.3.dist-info/METADATA
cryptoserpent-0.0.3.dist-info/WHEEL
cryptoserpent-0.0.3.dist-info/top_level.txt
cryptoserpent-0.0.3.dist-info/RECORD
