Metadata-Version: 2.1
Name: cryptoserpent
Version: 0.0.3
Summary: A python library for encryption
Author: Anish Kanthamneni
Author-email: akneni@gmail.com
Requires-Dist: numpy
